{"cameraMode":{"drawMode":0,"name":"Shaded","section":"Shading Mode"},"sceneLighting":true,"audioPlay":false,"sceneViewState":{"m_AlwaysRefresh":false,"showFog":true,"showSkybox":true,"showFlares":true,"showImageEffects":true,"showParticleSystems":true,"showVisualEffectGraphs":true,"m_FxEnabled":true},"in2DMode":false,"pivot":{"x":1.0292353630065919,"y":-6.6047563552856449,"z":27.31963539123535},"rotation":{"x":-0.18579070270061494,"y":-0.09768541157245636,"z":0.018543073907494546,"w":-0.9775819778442383},"size":16.344209671020509,"orthographic":false}